vue_cinema/__init__.py
vue_cinema/cinema.py
vue_cinema/movie.py
vue_cinema/shared.py
vue_cinema/showing.py
vue_cinema-0.0.0.dist-info/LICENCE
vue_cinema-0.0.0.dist-info/METADATA
vue_cinema-0.0.0.dist-info/WHEEL
vue_cinema-0.0.0.dist-info/top_level.txt
vue_cinema-0.0.0.dist-info/RECORD
