Metadata-Version: 2.1
Name: vue-cinema
Version: 0.0.0
Summary: A library to access information about vue cinemas
Home-page: https://github.com/DevFlock/vue-cinema
Author: Flonc
Project-URL: Documentation, https://github.com/DevFlock/vue-cinema
Project-URL: Bug Reports, https://github.com/DevFlock/vue-cinema/issues
Project-URL: Source Code, https://github.com/DevFlock/vue-cinema
Keywords: package,vue,cinema,api
Classifier: Development Status :: 3 - Alpha
Classifier: Intended Audience :: Developers
Classifier: Programming Language :: Python :: 3.10
Classifier: License :: OSI Approved :: MIT License
Classifier: Operating System :: OS Independent
Requires-Python: >=3.10
License-File: LICENCE
Requires-Dist: requests (~=2.28.1)
